psm_utils/__init__.py
psm_utils/__main__.py
psm_utils/exceptions.py
psm_utils/peptidoform.py
psm_utils/psm.py
psm_utils/psm_list.py
psm_utils/utils.py
psm_utils/io/__init__.py
psm_utils/io/_base_classes.py
psm_utils/io/_pd_msf_tables.py
psm_utils/io/_utils.py
psm_utils/io/alphadia.py
psm_utils/io/cbor.py
psm_utils/io/diann.py
psm_utils/io/exceptions.py
psm_utils/io/flashlfq.py
psm_utils/io/fragpipe.py
psm_utils/io/idxml.py
psm_utils/io/ionbot.py
psm_utils/io/json.py
psm_utils/io/maxquant.py
psm_utils/io/msamanda.py
psm_utils/io/mzid.py
psm_utils/io/parquet.py
psm_utils/io/peptide_record.py
psm_utils/io/pepxml.py
psm_utils/io/percolator.py
psm_utils/io/proteome_discoverer.py
psm_utils/io/proteoscape.py
psm_utils/io/sage.py
psm_utils/io/tsv.py
psm_utils/io/xtandem.py
psm_utils-1.5.1.dist-info/licenses/LICENSE
psm_utils-1.5.1.dist-info/METADATA
psm_utils-1.5.1.dist-info/WHEEL
psm_utils-1.5.1.dist-info/entry_points.txt
psm_utils-1.5.1.dist-info/top_level.txt
psm_utils-1.5.1.dist-info/RECORD
