Metadata-Version: 2.4
Name: psm-utils
Version: 1.5.1
Summary: Common utilities for parsing and handling peptide-spectrum matches and search engine results.
Author-email: Ralf Gabriels <ralf@gabriels.dev>, Robbin Bouwmeester <robbin.bouwmeester@ugent.be>, Arthur Declercq <arthur.declercq@ugent.be>
License-Expression: Apache-2.0
Project-URL: GitHub, https://github.com/compomics/psm_utils
Project-URL: ReadTheDocs, https://psm-utils.readthedocs.io
Project-URL: PyPi, https://pypi.org/project/psm-utils/
Project-URL: CompOmics, https://www.compomics.com
Keywords: proteomics,peptide,spectrum,identification,parsing
Classifier: Intended Audience :: Science/Research
Classifier: Operating System :: OS Independent
Classifier: Programming Language :: Python :: 3 :: Only
Classifier: Topic :: Scientific/Engineering :: Bio-Informatics
Classifier: Development Status :: 4 - Beta
Requires-Python: >=3.10
License-File: LICENSE
Requires-Dist: click
Requires-Dist: lxml
Requires-Dist: numpy
Requires-Dist: pandas
Requires-Dist: psims
Requires-Dist: pyarrow
Requires-Dist: pydantic>=2
Requires-Dist: pyteomics>=4
Requires-Dist: rich
Requires-Dist: sqlalchemy>=2
Provides-Extra: dev
Requires-Dist: ruff; extra == "dev"
Requires-Dist: isort>5; extra == "dev"
Requires-Dist: pytest; extra == "dev"
Requires-Dist: pytest-cov; extra == "dev"
Requires-Dist: mypy; extra == "dev"
Provides-Extra: docs
Requires-Dist: numpydoc<2,>=1; extra == "docs"
Requires-Dist: recommonmark; extra == "docs"
Requires-Dist: semver>=2; extra == "docs"
Requires-Dist: sphinx_rtd_theme; extra == "docs"
Requires-Dist: sphinx-autobuild; extra == "docs"
Requires-Dist: sphinx-mdinclude; extra == "docs"
Requires-Dist: sphinx; extra == "docs"
Requires-Dist: toml; extra == "docs"
Provides-Extra: online
Requires-Dist: streamlit; extra == "online"
Requires-Dist: plotly; extra == "online"
Provides-Extra: idxml
Requires-Dist: pyopenms; extra == "idxml"
Provides-Extra: cbor
Requires-Dist: cbor2>=5; extra == "cbor"
Provides-Extra: io
Requires-Dist: pyopenms; extra == "io"
Requires-Dist: cbor2>=5; extra == "io"
Dynamic: license-file
